pynanovnav2/__init__.py
pynanovnav2/nanovnav2.py
pynanovnav2/util_fetch.py
pynanovnav2/vectornetworkanalyzer.py
pynanovnav2_tspspi-0.0.1.dist-info/LICENSE.md
pynanovnav2_tspspi-0.0.1.dist-info/METADATA
pynanovnav2_tspspi-0.0.1.dist-info/WHEEL
pynanovnav2_tspspi-0.0.1.dist-info/entry_points.txt
pynanovnav2_tspspi-0.0.1.dist-info/top_level.txt
pynanovnav2_tspspi-0.0.1.dist-info/RECORD
