Metadata-Version: 2.1
Name: pynanovnav2-tspspi
Version: 0.0.1
Summary: NanoVNA2 Python libraries and tools (unofficial)
Home-page: https://github.com/tspspi/pynanovnav2
Author: Thomas Spielauer
Author-email: pypipackages01@tspi.at
Classifier: Programming Language :: Python :: 3
Classifier: License :: OSI Approved :: BSD License
Classifier: Operating System :: OS Independent
Requires-Python: >=3.6
License-File: LICENSE.md
Requires-Dist: pylabdevs-tspspi >=0.0.11
Requires-Dist: pyserial >=3.5
